health_gorilla_api/__init__.py
health_gorilla_api/api.py
health_gorilla_api-0.1.0.dist-info/METADATA
health_gorilla_api-0.1.0.dist-info/WHEEL
health_gorilla_api-0.1.0.dist-info/top_level.txt
health_gorilla_api-0.1.0.dist-info/RECORD
