Metadata-Version: 2.1
Name: health-gorilla-api
Version: 0.1.0
Summary: API for consuming health gorilla endpoints.
Home-page: UNKNOWN
Author: David Granados
Author-email: davidgranados@ballastlane.com
License: MIT
Platform: UNKNOWN
Classifier: Programming Language :: Python :: 3.6
Requires-Python: >=3.9.0
Requires-Dist: PyJWT (==2.5.0)
Requires-Dist: requests (==2.28.1)
